Metadata-Version: 2.1
Name: django-ghost
Version: 0.3.0
Summary: Django Ghost is a Django app to sync a Django model with Ghost CMS newsletter subscribers
Home-page: http://github.com/bitsy-ai/django-ghost
Author: Leigh Johnson
Author-email: leigh@bitsy.ai
License: BSD
Keywords: django ghost cms
Platform: UNKNOWN
Classifier: Programming Language :: Python :: 3.9
Classifier: Programming Language :: Python :: 3.10
Classifier: Programming Language :: Python :: 3.11
Classifier: Framework :: Django
Classifier: Framework :: Django :: 3.2
Classifier: Framework :: Django :: 4.1
Classifier: Framework :: Django :: 4.2
Requires-Python: >3.9
License-File: LICENSE
Requires-Dist: PyJWT
Requires-Dist: django
Requires-Dist: psycopg2
Requires-Dist: requests
